flet_blur/__init__.py
flet_blur/flet_blur.py
flutter/flet_blur/CHANGELOG.md
flutter/flet_blur/LICENSE
flutter/flet_blur/README.md
flutter/flet_blur/pubspec.yaml
flutter/flet_blur/lib/flet_blur.dart
flutter/flet_blur/lib/src/create_control.dart
flutter/flet_blur/lib/src/flet_blur.dart
flet_blur-0.3.0.dist-info/METADATA
flet_blur-0.3.0.dist-info/WHEEL
flet_blur-0.3.0.dist-info/top_level.txt
flet_blur-0.3.0.dist-info/RECORD
