Metadata-Version: 2.2
Name: flet-blur
Version: 0.3.0
Summary: Blur control for Flet
Author-email: KOGA Mitsuhiro <shiena.jp@gmail.com>
Project-URL: Homepage, https://github.com/shiena/flet-blur
Project-URL: Documentation, https://github.com/shiena/flet-blur
Project-URL: Repository, https://github.com/shiena/flet-blur
Project-URL: Issues, https://github.com/shiena/flet-blur/issues
Classifier: License :: OSI Approved :: Apache Software License
Requires-Python: >=3.9
Requires-Dist: flet>=0.26.0
